oianalytics/__init__.py
oianalytics/api/__init__.py
oianalytics/api/_credentials.py
oianalytics/api/_dataframes/__init__.py
oianalytics/api/_dataframes/assets.py
oianalytics/api/_dataframes/azure_blob_sources.py
oianalytics/api/_dataframes/batches.py
oianalytics/api/_dataframes/dashboard.py
oianalytics/api/_dataframes/data.py
oianalytics/api/_dataframes/events.py
oianalytics/api/_dataframes/files.py
oianalytics/api/_dataframes/measurements.py
oianalytics/api/_dataframes/model_instances.py
oianalytics/api/_dataframes/profiles.py
oianalytics/api/_dataframes/quantities.py
oianalytics/api/_dataframes/tags.py
oianalytics/api/_dataframes/units.py
oianalytics/api/_dataframes/users.py
oianalytics/api/endpoints/__init__.py
oianalytics/api/endpoints/assets.py
oianalytics/api/endpoints/azure_blob_sources.py
oianalytics/api/endpoints/batches.py
oianalytics/api/endpoints/computation_jobs.py
oianalytics/api/endpoints/dashboard.py
oianalytics/api/endpoints/data.py
oianalytics/api/endpoints/events.py
oianalytics/api/endpoints/files.py
oianalytics/api/endpoints/measurements.py
oianalytics/api/endpoints/model_instances.py
oianalytics/api/endpoints/profiles.py
oianalytics/api/endpoints/quantities.py
oianalytics/api/endpoints/tags.py
oianalytics/api/endpoints/units.py
oianalytics/api/endpoints/users.py
oianalytics/api/utils.py
oianalytics/models/__init__.py
oianalytics/models/_dtos.py
oianalytics/models/_queries/__init__.py
oianalytics/models/_queries/files.py
oianalytics/models/_queries/instances.py
oianalytics/models/_queries/single_observation.py
oianalytics/models/_template_resources/__init__.py
oianalytics/models/_template_resources/file_processing_template.py
oianalytics/models/_template_resources/free_from_api_template.py
oianalytics/models/_template_resources/single_observation_template.py
oianalytics/models/outputs.py
oianalytics/models/templates.py
oianalytics/models/testing/__init__.py
oianalytics/models/testing/_mocking.py
oianalytics/models/testing/_tests_setup.py
oianalytics-0.6.12.dist-info/LICENSE
oianalytics-0.6.12.dist-info/METADATA
oianalytics-0.6.12.dist-info/WHEEL
oianalytics-0.6.12.dist-info/RECORD
