Metadata-Version: 2.1
Name: oianalytics
Version: 0.6.12
Summary: Python tools for working with OIAnalytics
License: EUPL-1.2
Author: Optimistik SAS
Author-email: arthur.martel@optimistik.fr
Requires-Python: >=3.9,<4.0
Classifier: License :: OSI Approved :: European Union Public Licence 1.2 (EUPL 1.2)
Classifier: Programming Language :: Python :: 3
Classifier: Programming Language :: Python :: 3.9
Classifier: Programming Language :: Python :: 3.10
Classifier: Programming Language :: Python :: 3.11
Classifier: Programming Language :: Python :: 3.12
Classifier: Programming Language :: Python :: 3.13
Requires-Dist: pandas (>=2.0.3)
Requires-Dist: pydantic (>=2.10.2)
Requires-Dist: requests (>=2.26.0)
